gnoman/__init__.py
gnoman/__main__.py
gnoman/core.py
gnoman/tui.py
gnoman/cli/__init__.py
gnoman/cli/audit.py
gnoman/cli/guard.py
gnoman/cli/plugin.py
gnoman/cli/safe.py
gnoman/cli/secrets.py
gnoman/cli/tx.py
gnoman/utils/__init__.py
gnoman/utils/logbook.py
gnoman_cli-0.2.3.dist-info/licenses/LICENSE.md
gnoman_cli-0.2.3.dist-info/METADATA
gnoman_cli-0.2.3.dist-info/WHEEL
gnoman_cli-0.2.3.dist-info/entry_points.txt
gnoman_cli-0.2.3.dist-info/top_level.txt
gnoman_cli-0.2.3.dist-info/RECORD
