Metadata-Version: 2.4
Name: gnoman-cli
Version: 0.2.3
Summary: GNOMAN mission control CLI for Safes, secrets, and guard rails
Author-email: Christopher Hirschauer <c.hirschauer@gmail.com>
License-Expression: MIT
Project-URL: Homepage, https://github.com/74Thirsty/gnoman-cli
Project-URL: Source, https://github.com/74Thirsty/gnoman-cli
Project-URL: Issues, https://github.com/74Thirsty/gnoman-cli/issues
Classifier: Programming Language :: Python :: 3
Classifier: Programming Language :: Python :: 3.9
Classifier: Programming Language :: Python :: 3.10
Classifier: Programming Language :: Python :: 3.11
Classifier: Environment :: Console
Classifier: Topic :: Security :: Cryptography
Classifier: Topic :: Internet :: WWW/HTTP
Classifier: Operating System :: OS Independent
Requires-Python: >=3.9
License-File: LICENSE.md
Requires-Dist: eth-account
Requires-Dist: web3>=6
Requires-Dist: eth-abi
Requires-Dist: pycryptodome; python_version < "3.11"
Requires-Dist: cryptography
Requires-Dist: keyring
Requires-Dist: python-dotenv
Requires-Dist: rich
Provides-Extra: dev
Requires-Dist: pytest; extra == "dev"
Requires-Dist: black; extra == "dev"
Requires-Dist: build; extra == "dev"
Requires-Dist: twine; extra == "dev"
Dynamic: license-file
